ruamel.music-0.5.0-py3.10-nspkg.pth
ruamel/music/__init__.py
ruamel/music/__main__.py
ruamel/music/albumtype.py
ruamel/music/music.py
ruamel/music/stemanalyser.py
ruamel.music-0.5.0.dist-info/METADATA
ruamel.music-0.5.0.dist-info/WHEEL
ruamel.music-0.5.0.dist-info/entry_points.txt
ruamel.music-0.5.0.dist-info/namespace_packages.txt
ruamel.music-0.5.0.dist-info/top_level.txt
ruamel.music-0.5.0.dist-info/RECORD
